haystack_integrations/components/embedders/gradient/__init__.py
haystack_integrations/components/embedders/gradient/gradient_document_embedder.py
haystack_integrations/components/embedders/gradient/gradient_text_embedder.py
haystack_integrations/components/generators/gradient/__init__.py
haystack_integrations/components/generators/gradient/base.py
gradient_haystack-0.4.0.dist-info/METADATA
gradient_haystack-0.4.0.dist-info/WHEEL
gradient_haystack-0.4.0.dist-info/licenses/LICENSE.txt
gradient_haystack-0.4.0.dist-info/RECORD
